README.md
setup.py
blockhub_slackbot.egg-info/PKG-INFO
blockhub_slackbot.egg-info/SOURCES.txt
blockhub_slackbot.egg-info/dependency_links.txt
blockhub_slackbot.egg-info/requires.txt
blockhub_slackbot.egg-info/top_level.txt
slackbot/__init__.py
slackbot/attachments.py
slackbot/helpers.py