Metadata-Version: 1.0
Name: blockhub-slackbot
Version: 0.0.2
Summary: liteweight synchronous botframework for slack
Home-page: https://github.com/blockhub/slackbot
Author: Charles
Author-email: karel@blockhub.nl
License: MIT
Platform: UNKNOWN
